hlpl_arabic_words/__init__.py
hlpl_arabic_words/__main__.py
hlpl_arabic_words/arabic_words.py
hlpl_arabic_words/hlpl_arabic_words.db
hlpl_arabic_words/setup.cfg
hlpl_arabic_words-1.0.2.dist-info/LICENSE
hlpl_arabic_words-1.0.2.dist-info/METADATA
hlpl_arabic_words-1.0.2.dist-info/WHEEL
hlpl_arabic_words-1.0.2.dist-info/entry_points.txt
hlpl_arabic_words-1.0.2.dist-info/top_level.txt
hlpl_arabic_words-1.0.2.dist-info/RECORD
