Metadata-Version: 2.1
Name: hlpl-arabic-words
Version: 1.0.2
Summary: hlpl_arabic_words lists nouns, verbs, articles, nouns prefix, nouns suffix, verbs prefix, and verbs suffix in a readable database file
Home-page: https://hlpl.net/resource/
Author: Ahmida Bendjoudi
Author-email: email@hlpl.net
License: MIT
Download-URL: https://hlpl.net/resource//download/
Project-URL: hlpl, https://hlpl.net
Project-URL: hlpl_arabic_words-docs, https://docs.hlpl.net
Project-URL: hlpl_arabic_words-forum, https://hlpl.net
Project-URL: hlpl_arabic_words-github, https://github.com/hlpl/arabic-words
Keywords: hlpl_arabic_words,hlpl arabic words,arabic words,hlpl arabic words,hlpl
Platform: UNKNOWN
Classifier: Natural Language :: Arabic
